silicon/__init__.py
silicon/cell.py
silicon/cluster.py
silicon/ensemble.py
silicon/utils.py
silicon_clustering-0.3.1.dist-info/DESCRIPTION.rst
silicon_clustering-0.3.1.dist-info/METADATA
silicon_clustering-0.3.1.dist-info/RECORD
silicon_clustering-0.3.1.dist-info/WHEEL
silicon_clustering-0.3.1.dist-info/metadata.json
silicon_clustering-0.3.1.dist-info/top_level.txt
silicon_clustering-0.3.1.dist-info/zip-safe
