Metadata-Version: 1.1
Name: silicon-clustering
Version: 0.3.1
Summary: Single-linkage connectivity clustering by cosine similarity
Home-page: https://github.com/CZ-NIC/silicon-clustering
Author: Tomas Gavenciak
Author-email: gavento@ucw.cz
License: MIT
Keywords: connectivity clustering similarity PCA
Platform: UNKNOWN
Classifier: Development Status :: 3 - Alpha
Classifier: Intended Audience :: Science/Research
Classifier: Programming Language :: Python :: 3
Classifier: Programming Language :: Python :: 2.7
Classifier: Topic :: Scientific/Engineering :: Information Analysis
